uhkamalli/__init__.py
uhkamalli/__main__.py
uhkamalli/cli.py
uhkamalli/uhkamalli.py
uhkamalli-2023.10.22.dist-info/LICENSE
uhkamalli-2023.10.22.dist-info/METADATA
uhkamalli-2023.10.22.dist-info/WHEEL
uhkamalli-2023.10.22.dist-info/entry_points.txt
uhkamalli-2023.10.22.dist-info/top_level.txt
uhkamalli-2023.10.22.dist-info/RECORD
